[
  {
    "id": "a6d9d783-d546-4afc-b31e-800917cdd2d6",
    "email": "zy910826@163.com",
    "createdAt": "2026-01-30T15:09:51.192Z",
    "form": {
      "name": "",
      "gender": "女",
      "birthday": "1991-08-26",
      "birthTime": "20:00",
      "birthplace": ""
    },
    "panelInput": {
      "birthday": "1991-08-26",
      "birthTime": 10,
      "gender": "女",
      "birthdayType": "solar",
      "fixLeap": true,
      "lang": "zh-CN"
    }
  },
  {
    "id": "0332521b-4a75-4841-a2eb-8d8b0081babf",
    "email": "zy910826@163.com",
    "createdAt": "2026-01-30T15:10:06.922Z",
    "form": {
      "name": "3",
      "gender": "女",
      "birthday": "1991-08-26",
      "birthTime": "12:00",
      "birthplace": ""
    },
    "panelInput": {
      "birthday": "1991-08-26",
      "birthTime": 6,
      "gender": "女",
      "birthdayType": "solar",
      "fixLeap": true,
      "lang": "zh-CN"
    }
  }
]